anima/__init__.py
anima/navigation.py
anima/static/css/base.css
anima/static/fonts/fa-brands-400.eot
anima/static/fonts/fa-brands-400.svg
anima/static/fonts/fa-brands-400.ttf
anima/static/fonts/fa-brands-400.woff
anima/static/fonts/fa-brands-400.woff2
anima/static/fonts/fa-solid-900.eot
anima/static/fonts/fa-solid-900.svg
anima/static/fonts/fa-solid-900.ttf
anima/static/fonts/fa-solid-900.woff
anima/static/fonts/fa-solid-900.woff2
anima/static/fonts/pigpenencryption.woff
anima/static/fonts/pigpenencryption.woff2
anima/static/img/anima.png
anima/static/img/favicon.ico
anima/static/img/separateur.png
anima/templates/404.html
anima/templates/background.html
anima/templates/index.html
anima/templates/squelette.html
anima/templates/acte-1/acte-1.html
anima/templates/acte-1/aventure-1.html
anima/templates/acte-1/index.html
anima/templates/acte-1/introduction.html
anima_campaign-0.2.dist-info/LICENSE
anima_campaign-0.2.dist-info/METADATA
anima_campaign-0.2.dist-info/WHEEL
anima_campaign-0.2.dist-info/entry_points.txt
anima_campaign-0.2.dist-info/top_level.txt
anima_campaign-0.2.dist-info/zip-safe
anima_campaign-0.2.dist-info/RECORD
